docx_extractor/__init__.py
docx_extractor/core.py
docx_extractor/main.py
docx_extractor/processors.py
docx_extractor/toon_formatter.py
docx_extractor-1.0.0.dist-info/METADATA
docx_extractor-1.0.0.dist-info/WHEEL
docx_extractor-1.0.0.dist-info/entry_points.txt
docx_extractor-1.0.0.dist-info/top_level.txt
docx_extractor-1.0.0.dist-info/RECORD
