Metadata-Version: 2.4
Name: docx-extractor
Version: 1.0.0
Summary: Recursive DOCX extractor with embedded files support
Author-email: S C Arham <arhamscoff@gmail.com>
License-Expression: MIT
Classifier: Programming Language :: Python :: 3
Requires-Python: >=3.8
Requires-Dist: python-docx>=1.1.0
Requires-Dist: openpyxl>=3.1.0
Requires-Dist: olefile>=0.46
